clientai/__init__.py
clientai/_common_types.py
clientai/_constants.py
clientai/_typing.py
clientai/agent/__init__.py
clientai/agent/config/__init__.py
clientai/agent/config/defaults.py
clientai/agent/config/models.py
clientai/agent/config/steps.py
clientai/agent/config/tools.py
clientai/agent/core/__init__.py
clientai/agent/core/agent.py
clientai/agent/core/context.py
clientai/agent/core/execution.py
clientai/agent/core/factory.py
clientai/agent/core/workflow.py
clientai/agent/exceptions.py
clientai/agent/formatting/__init__.py
clientai/agent/formatting/formatter.py
clientai/agent/formatting/options.py
clientai/agent/steps/__init__.py
clientai/agent/steps/base.py
clientai/agent/steps/decorators.py
clientai/agent/steps/registry.py
clientai/agent/steps/types.py
clientai/agent/tools/__init__.py
clientai/agent/tools/base.py
clientai/agent/tools/decorators.py
clientai/agent/tools/registry.py
clientai/agent/tools/selection/__init__.py
clientai/agent/tools/selection/config.py
clientai/agent/tools/selection/selector.py
clientai/agent/tools/types.py
clientai/agent/types/__init__.py
clientai/agent/types/common.py
clientai/agent/types/models.py
clientai/agent/types/protocols.py
clientai/agent/utils/__init__.py
clientai/agent/utils/exceptions.py
clientai/agent/utils/validation.py
clientai/agent/validation/__init__.py
clientai/agent/validation/base.py
clientai/agent/validation/exceptions.py
clientai/agent/validation/result.py
clientai/agent/validation/types.py
clientai/ai_provider.py
clientai/client_ai.py
clientai/exceptions.py
clientai/groq/__init__.py
clientai/groq/_typing.py
clientai/groq/provider.py
clientai/ollama/__init__.py
clientai/ollama/_typing.py
clientai/ollama/manager/__init__.py
clientai/ollama/manager/config.py
clientai/ollama/manager/core.py
clientai/ollama/manager/exceptions.py
clientai/ollama/manager/platform_info.py
clientai/ollama/provider.py
clientai/openai/__init__.py
clientai/openai/_typing.py
clientai/openai/provider.py
clientai/py.typed
clientai-0.5.0.dist-info/LICENSE
clientai-0.5.0.dist-info/METADATA
clientai-0.5.0.dist-info/WHEEL
clientai-0.5.0.dist-info/RECORD
