Metadata-Version: 2.1
Name: clientai
Version: 0.5.0
Summary: A unified client for AI providers with built-in agent support.
Keywords: ai,agents,llm,nlp,language-model,ai-agents
Author: Igor Benav
Author-email: igor.magalhaes.r@gmail.com
Requires-Python: >=3.9,<4.0
Classifier: Development Status :: 4 - Beta
Classifier: Intended Audience :: Developers
Classifier: Intended Audience :: Information Technology
Classifier: Intended Audience :: Science/Research
Classifier: Intended Audience :: System Administrators
Classifier: License :: OSI Approved :: MIT License
Classifier: Operating System :: OS Independent
Classifier: Programming Language :: Python :: 3
Classifier: Programming Language :: Python :: 3.9
Classifier: Programming Language :: Python :: 3.10
Classifier: Programming Language :: Python :: 3.11
Classifier: Programming Language :: Python :: 3.12
Classifier: Programming Language :: Python :: 3.13
Classifier: Topic :: Scientific/Engineering :: Artificial Intelligence
Classifier: Topic :: Software Development :: Libraries
Classifier: Topic :: Software Development :: Libraries :: Python Modules
Classifier: Typing :: Typed
Provides-Extra: all
Provides-Extra: groq
Provides-Extra: minimal
Provides-Extra: ollama
Provides-Extra: openai
Provides-Extra: replicate
Requires-Dist: groq (>=0.11.0,<0.12.0) ; extra == "groq" or extra == "all"
Requires-Dist: httpx (>=0.27.0,<0.28.0) ; extra == "openai" or extra == "groq" or extra == "all"
Requires-Dist: ollama (>=0.3.3,<0.4.0) ; extra == "ollama" or extra == "all"
Requires-Dist: openai (>=1.50.2,<2.0.0) ; extra == "openai" or extra == "all"
Requires-Dist: pydantic (>=2.10.3,<3.0.0)
Requires-Dist: replicate (>=0.34.1,<0.35.0) ; extra == "replicate" or extra == "all"
